DatosBook/__init__.py
DatosBook/_modidx.py
DatosBook/core.py
DatosBook-0.0.1.dist-info/LICENSE
DatosBook-0.0.1.dist-info/METADATA
DatosBook-0.0.1.dist-info/WHEEL
DatosBook-0.0.1.dist-info/entry_points.txt
DatosBook-0.0.1.dist-info/top_level.txt
DatosBook-0.0.1.dist-info/RECORD
