Metadata-Version: 2.1
Name: DatosBook
Version: 0.0.1
Summary: Repositorio pque recolecta el contenido de Ingeniería de Datos y lo presenta en una página web usando nbdev.
Home-page: https://github.com/dci-courses/DatosBook
Author: Germán Jara
Author-email: g.jara08@ufromail.cl
License: Apache Software License 2.0
Keywords: nbdev jupyter notebook python
Classifier: Development Status :: 4 - Beta
Classifier: Intended Audience :: Developers
Classifier: Natural Language :: English
Classifier: Programming Language :: Python :: 3.7
Classifier: Programming Language :: Python :: 3.8
Classifier: Programming Language :: Python :: 3.9
Classifier: Programming Language :: Python :: 3.10
Classifier: License :: OSI Approved :: Apache Software License
Requires-Python: >=3.7
License-File: LICENSE
Requires-Dist: fastcore
Requires-Dist: pandas
Requires-Dist: mlxtend
Provides-Extra: dev
Requires-Dist: fastcore; extra == "dev"
Requires-Dist: pandas; extra == "dev"
Requires-Dist: mlxtend; extra == "dev"
